pinna
