Metadata-Version: 1.1
Name: pinna
Version: 0.1.0
Summary: Tools for creating and listening to google alerts
Home-page: http://github.com/newslynx/pinna
Author: Brian Abelson
Author-email: brian@newslynx.org
License: MIT
Platform: UNKNOWN
Classifier: Development Status :: 3 - Alpha
Classifier: Intended Audience :: Developers
Classifier: License :: OSI Approved :: MIT License
Classifier: Operating System :: OS Independent
Classifier: Programming Language :: Python
